debugdata/__init__.py
debugdata-0.0.1.dist-info/LICENSE
debugdata-0.0.1.dist-info/METADATA
debugdata-0.0.1.dist-info/WHEEL
debugdata-0.0.1.dist-info/top_level.txt
debugdata-0.0.1.dist-info/RECORD
